README.md
redisqueue.py
rockettm.py
rockettm_server.py
setup.py
rockettm.egg-info/PKG-INFO
rockettm.egg-info/SOURCES.txt
rockettm.egg-info/dependency_links.txt
rockettm.egg-info/entry_points.txt
rockettm.egg-info/not-zip-safe
rockettm.egg-info/requires.txt
rockettm.egg-info/top_level.txt